{"cameraMode":{"drawMode":0,"name":"Shaded","section":"Shading Mode"},"sceneLighting":false,"audioPlay":false,"sceneViewState":{"showFog":true,"showMaterialUpdate":false,"showSkybox":false,"showFlares":true,"showImageEffects":true,"showParticleSystems":true},"in2DMode":false,"pivot":{"x":-7.768552303314209,"y":2.731168508529663,"z":-4.933934688568115},"rotation":{"x":0.16351664066314698,"y":0.4038506746292114,"z":-0.07364873588085175,"w":0.897091805934906},"size":12.999938011169434,"orthographic":false}